{
  "4": [
    "3407865783",
    "3466311047",
    "3473327417",
    "3473418978",
    "3473600431",
    "3551084564",
    "3757100662",
    "3833739592",
    "3845833068",
    "3963471476",
    "B0F3CT4RK1",
    "B0FDPTX1MY"
  ],
  "3": [
    "B074ZCWJ1F",
    "B08J4XBMJJ",
    "B0B213Q1Z7",
    "B0B61D1SH1",
    "B0BW9MNYBZ",
    "B0CLB74C2C",
    "B0CRVRTJMY",
    "B0CTHYMKJG",
    "B0DLWK3LKH",
    "B0DSPQM8B9",
    "B0F635CTN3"
  ],
  "1": [
    "B07XZPV2RJ",
    "B08J4WVYL8",
    "B08P9V4DSX",
    "B09GG7LYV6",
    "B09KS5HT2R",
    "B0B214SPFN",
    "B0BZ48QC9Q",
    "B0C2HH97LD",
    "B0C696BHZ8",
    "B0CJ99TKF3",
    "B0CLDZDRBP",
    "B0CRS4DJ4R",
    "B0CTHWK5GJ",
    "B0D6GHTF4W",
    "B0DKNM9NWR",
    "B0DWXVCNPD",
    "B0F3XTHXZK",
    "B0F66YYWFL",
    "B0FR8X2J3V"
  ],
  "5": [
    "B082B1W1NG",
    "B0897GGD4F",
    "B098K7J41D",
    "B0C7G83BC4",
    "B0CLGPJBNJ",
    "B0CNRNHCHZ",
    "B0CSKCB3JX",
    "B0DF4Y4WQJ",
    "B0DWXB4MB3",
    "B0DY1MJQ76"
  ],
  "2": [
    "B08J4Y9BD4",
    "B08WH8CSY4",
    "B0C2YWGYL2",
    "B0D1QZR6PG",
    "B0D6GKPLR8",
    "B0D6GL5CL3",
    "B0DDLCJ9XF",
    "B0F79RJ6C6",
    "B0FCS3LW64",
    "B0FH4ML22K",
    "B0FRLBQ19P",
    "B0FT36X6R2"
  ]
}