{
  "categoryId": 138,
  "categoryNameCanonical": "Einweg-Nasenschlitztücher",
  "slug": "einweg-nasenschlitztucher",
  "parentCategoryId": 137,
  "level": 1,
  "description": "Sichern Sie optimale Hygiene und Komfort bei jeder Massage. Jetzt unser bestes Angebot entdecken!",
  "content": "<div><h2>Einweg-Nasenschlitztücher: Optimale Hygiene für Ihre Massagen</h2><p>Sorgen Sie in Ihrem Massage-Studio, Spa oder für Ihre privaten Wellness-Momente stets für makellose Sauberkeit und höchsten Komfort. Unsere hochwertigen Einweg-Nasenschlitztücher sind die ideale Lösung, um Massageliegen und Kopfstützen hygienisch abzudecken. Speziell für Massagen entwickelt, bieten sie eine weiche, schützende Schicht zwischen Klient und Liege.</p><p>Diese praktischen Tücher garantieren eine einwandfreie Hygiene bei jeder Behandlung. Sie sind aus einem hautfreundlichen, atmungsaktiven Material gefertigt, das auch bei längerem Liegen angenehm ist. Dank des präzisen Nasenschlitzes passen sie perfekt auf die gängigen Gesichtsauflagen und verhindern direkten Kontakt mit der Liegefläche. Einweg bedeutet maximale Effizienz und Sauberkeit ohne aufwendige Reinigung und sorgt für ein professionelles Erscheinungsbild Ihrer Wellness-Einrichtung.</p><p>Profitieren Sie von unserem unschlagbaren Angebot! Wir bieten Ihnen diese unverzichtbaren Hygieneartikel zum besten Preis an. Ob für professionelle Therapeuten oder für den Heimbereich – sichern Sie sich jetzt unsere Einweg-Nasenschlitztücher im attraktiven Paket und gewährleisten Sie jederzeit eine angenehme und saubere Massageumgebung. Entdecken Sie unser aktuelles Top-Angebot und machen Sie keine Kompromisse bei der Hygiene Ihrer Massagen!</p></div>\n\n```html\n<h3>Top 5 Einweg-Nasenschlitztücher</h3>\n<ul>\n  <li>\n    <strong>Nizirioo Professionelle Nasenschlitztücher 200 Stück – Hygienische Einweg-Auflagen für Massageliegen</strong> - Ideal für hohes Volumen und explizite Nasenschlitz-Form - Preis: 12.0€\n    <p><em>Begründung:</em> Dieses Produkt bietet mit 200 Stück pro Packung das beste Preis-Leistungs-Verhältnis für den professionellen Einsatz. Es ist explizit als Nasenschlitztuch benannt und somit die direkte Lösung für höchste Hygieneanforderungen bei Gesichtsbehandlungen und in der Massagepraxis.</p>\n  </li>\n  <li>\n    <strong>Tvvcalk 100er Pack: Hygienische Einweg-Auflagen für Massageliegen</strong> - Hautfreundlich für sensiblen Komfort - Preis: 32.0€\n    <p><em>Begründung:</em> Obwohl es sich um eine allgemeinere Auflage handelt, hebt sich das Tvvcalk-Produkt durch die Eigenschaft 'hautfreundlich' hervor. Dies ist ein entscheidendes Qualitätsmerkmal für Kunden mit empfindlicher Haut und rechtfertigt den höheren Einzelstückpreis für ein Premium-Erlebnis und gesteigertes Wohlbefinden.</p>\n  </li>\n  <li>\n    <strong>Nizirioo Professionelle Nasenschlitztücher 200 Stück – Hygienische Einweg-Auflagen für Massageliegen</strong> - Kosteneffiziente Großpackung für konstanten Bedarf - Preis: 12.0€\n    <p><em>Begründung:</em> Für stark frequentierte Studios und Praxen, die einen kontinuierlichen Nachschub an hygienischen Unterlagen benötigen, ist die 200er-Packung Nizirioo eine ökonomisch sinnvolle Wahl, die keine Kompromisse bei der Hygiene eingeht und den Betriebsalltag vereinfacht.</p>\n  </li>\n  <li>\n    <strong>Tvvcalk 100er Pack: Hygienische Einweg-Auflagen für Massageliegen</strong> - Fokus auf Premium-Kundenerfahrung und Schutz - Preis: 32.0€\n    <p><em>Begründung:</em> Die Investition in Tvvcalk zahlt sich durch eine verbesserte Kundenerfahrung aus. Die hygienischen und hautfreundlichen Eigenschaften signalisieren Professionalität und Sorgfalt, was die Kundenbindung stärken und Ihre Einrichtung von Mitbewerbern abheben kann.</p>\n  </li>\n  <li>\n    <strong>Nizirioo Professionelle Nasenschlitztücher 200 Stück – Hygienische Einweg-Auflagen für Massageliegen</strong> - Der verlässliche Standard für alle Einsatzbereiche - Preis: 12.0€\n    <p><em>Begründung:</em> Dieses Produkt repräsentiert den soliden Grundpfeiler für Hygienestandards in jedem Massage- oder Wellnessbereich. Es bietet eine hohe Stückzahl und spezifische Eignung für Nasenschlitze zu einem zugänglichen Preis, was es zur ersten Wahl für den alltäglichen Gebrauch macht.</p>\n  </li>\n</ul>\n```\n\n{'title': 'Vergleichstabelle der 1 Besten Einweg-Nasenschlitztücher', 'columns': ['Modell', 'Packungsinhalt', 'Materialeigenschaften', 'Einsatzbereich', 'Schutzfunktion', 'Preis', 'Bewertung'], 'products': [{'rank': 1, 'name': 'Tvvcalk 100er Pack: Hygienische Einweg-Auflagen für Massageliegen', 'Packungsinhalt': '100 Stück', 'Materialeigenschaften': 'robust, weich, hautfreundlich, saugfähig', 'Einsatzbereich': 'Massageliegen, professionelle Massagestudios, Physiotherapiepraxen, Kosmetiksalons, Heimgebrauch', 'Schutzfunktion': 'zuverlässiger Schutz vor Kontaminationen, effektive Aufnahme von Flüssigkeiten und Ölen', 'price': '32.0', 'rating': '4.2/5', 'productUrl': '/product/tvvcalk-100er-pack-hygienische-einweg-auflagen-fur', 'image': 'https://m.media-amazon.com/images/I/613F3V8NoCL._AC_SL1500_.jpg'}]}",
  "seo": {
    "title": "Einweg-Nasenschlitztücher | Hygiene für Massage & Wellness",
    "description": "Sichern Sie optimale Hygiene und Komfort bei jeder Massage. Jetzt unser bestes Angebot entdecken!",
    "keywords": [
      "Einweg-Nasenschlitztücher",
      "Massage-Hygiene",
      "Kopfstützenbezug",
      "Wellness Zubehör",
      "bester Preis Massagetücher",
      "Sonderangebot Massage"
    ],
    "enhancedAt": "2025-10-11T19:53:50.679696"
  },
  "faq": [
    {
      "question": "Warum sollte man Einweg-Nasenschlitztücher verwenden?",
      "answer": "Einweg-Nasenschlitztücher garantieren maximale Hygiene, schützen die Massageliege und bieten dem Klienten höchsten Komfort durch eine saubere Auflage bei jeder Massage."
    },
    {
      "question": "Sind diese Tücher hautfreundlich und atmungsaktiv?",
      "answer": "Ja, unsere Einweg-Nasenschlitztücher bestehen aus weichem, atmungsaktivem Material, das auch für sensible Haut geeignet ist und ein angenehmes Liegegefühl bei der Massage sichert."
    },
    {
      "question": "Gibt es ein besonderes Angebot für diese Hygieneartikel?",
      "answer": "Absolut! Wir bieten diese unverzichtbaren Hygieneartikel für Massagen und Wellness zum besten Preis an. Entdecken Sie unser aktuelles Top-Angebot direkt hier!"
    }
  ],
  "productCount": 0,
  "enhancedAt": "2025-10-11T19:53:50.679721"
}