{
  "categoryId": 140,
  "categoryNameCanonical": "Desinfektionstücher & Reiniger",
  "slug": "desinfektionstucher-reiniger",
  "parentCategoryId": 137,
  "level": 1,
  "description": "Maximale Hygiene für Massage & Wellness. Desinfektionstücher & Reiniger – Top Angebote!",
  "content": "<div><h2>Perfekte Hygiene für Massage & Wellness: Desinfektionstücher & Reiniger</h2><p>In der Welt der <strong>Massage</strong> und des <strong>Wellness</strong> ist makellose Hygiene nicht nur ein Qualitätsmerkmal, sondern eine absolute Notwendigkeit. Unsere hochwertigen <strong>Desinfektionstücher & Reiniger</strong> bieten Ihnen die Sicherheit und Sauberkeit, die Ihre Klienten erwarten und die Ihre Praxis verdient. Schützen Sie sich und Ihre Kunden effektiv vor Keimen und Bakterien, um ein stets frisches und sicheres Umfeld zu gewährleisten.</p><p>Ein sauberes und desinfiziertes Umfeld schafft Vertrauen und fördert das Wohlbefinden. Unsere Produkte sind speziell darauf ausgelegt, alle Oberflächen in Ihrem Massage- oder Wellnessbereich gründlich und schonend zu reinigen und zu desinfizieren. Von der Massageliege bis zu den Geräten – mit unseren Reinigern sorgen Sie für einen hygienisch einwandfreien Zustand. Wir bieten eine breite Palette an Lösungen, die sowohl effektiv als auch einfach in der Anwendung sind, um Ihre täglichen Abläufe zu erleichtern.</p><p>Profitieren Sie von unserem <strong>besten Preis</strong> für hochwertige <strong>Desinfektionsmittel</strong>. Wir sind stets bemüht, Ihnen exzellente Produkte zu attraktiven Konditionen anzubieten. Halten Sie Ausschau nach unseren speziellen <strong>Angeboten</strong>, um Ihre Praxis optimal auszustatten und gleichzeitig Ihr Budget zu schonen. Mit unseren Desinfektionstüchern und Reinigern gewährleisten Sie nicht nur die Sicherheit, sondern auch das höchste Wohlbefinden all Ihrer Besucher. Machen Sie Hygiene zu Ihrem Markenzeichen und zeigen Sie Ihren Klienten, dass ihre Gesundheit und Sicherheit an erster Stelle stehen!</p></div>\n\n<h3>Top 5 Desinfektionstücher & Reiniger</h3>\n<ul>\n    <li>\n        <strong>Mikrozid® Universal Wipes Premium – Hocheffiziente Desinfektion, 6 x 100 Tücher</strong> - Hocheffiziente Großpackung für professionelle Nutzung - Prix: 51.0€<br>\n        Ideal für Bereiche mit hohem Hygienebedarf. Die große Packungsmenge bietet exzellentes Preis-Leistungs-Verhältnis bei gleichzeitig maximaler Wirksamkeit, perfekt für den Dauereinsatz in Praxis und Wellness.\n    </li>\n    <li>\n        <strong>Sagrotan Hygienereinigungstücher: 300er Pack für professionelle Desinfektion</strong> - Umfangreiche Desinfektion im praktischen Großpack - Prix: 19.0€<br>\n        Eine kostengünstige und bewährte Lösung für die professionelle Flächenreinigung. Bietet umfassenden Schutz und Sauberkeit für diverse Oberflächen, eine solide Wahl für den Alltag.\n    </li>\n    <li>\n        <strong>Sagrotan 2in1 Desinfektionstücher für Hände & Oberflächen</strong> - Vielseitige 2in1-Lösung für Hände und Flächen - Prix: 15.0€<br>\n        Perfekt für unterwegs und schnelle Hygiene zwischendurch. Bietet flexible Anwendung auf Haut und Oberflächen mit der bekannten Sagrotan-Qualität, ideal für Massage- und Wellnesstherapeuten auf Reisen.\n    </li>\n    <li>\n        <strong>Mikrozid® Universal Tücher | Schnell & Effektiv Desinfektion | 1 Stück</strong> - Schnelle und effektive Einzeldesinfektion - Prix: 16.0€<br>\n        Hervorragend für den punktuellen oder Testeinsatz. Bietet die hohe Desinfektionsleistung von Mikrozid in einer handlichen Einzelpackung, nützlich für gezielte Anwendungen oder zur Probenahme.\n    </li>\n    <li>\n        <strong>Bestseller</strong> - Beliebt und preiswert - Prix: 5.0€<br>\n        Ein erschwingliches Produkt, das sich großer Beliebtheit erfreut. Eine gute Option für grundlegende Reinigungsbedürfnisse mit einem attraktiven Preis und bewährter Qualität.\n    </li>\n</ul>\n\n{'title': 'Vergleichstabelle der Desinfektionstücher & Reiniger', 'columns': ['Modell', 'Anwendungsbereich', 'Packungsgröße', 'Wirksamkeit', 'Preis pro Tuch', 'Preis', 'Bewertung'], 'products': [{'rank': 1, 'name': 'Mikrozid® Universal Tücher', 'Anwendungsbereich': 'Universal, Oberflächen', 'Packungsgröße': '1 Tuch', 'Wirksamkeit': 'Schnell & Effektiv Desinfektion', 'Preis pro Tuch': '16.00', 'price': '16.0', 'rating': '4.7/5', 'productUrl': '/product/mikrozid-universal-tucher-schnell-effektiv-desinfektion', 'image': 'https://m.media-amazon.com/images/I/712fYIellvL._SL1500_.jpg'}, {'rank': 2, 'name': 'Sagrotan 2in1 Desinfektionstücher', 'Anwendungsbereich': 'Hände & Oberflächen', 'Packungsgröße': '15 Tücher', 'Wirksamkeit': 'Standard Desinfektion', 'Preis pro Tuch': '0.07', 'price': '1.0', 'rating': '4.7/5', 'productUrl': '/product/sagrotan-2in1-desinfektionstucher-fur-hande-oberflachen', 'image': 'https://m.media-amazon.com/images/I/61YMRUgADUL._AC_SL1500_.jpg'}]}",
  "seo": {
    "title": "Desinfektionstücher & Reiniger – Top Hygiene für Ihre Massagepraxis",
    "description": "Maximale Hygiene für Massage & Wellness. Desinfektionstücher & Reiniger – Top Angebote!",
    "keywords": [
      "Desinfektionstücher",
      "Reiniger Massage",
      "Hygiene Wellness",
      "Massage Zubehör",
      "bester Preis Desinfektion",
      "Angebot Reinigungsmittel",
      "Massageliege reinigen",
      "Wellness Desinfektion",
      "Oberflächenhygiene"
    ],
    "enhancedAt": "2025-10-11T19:53:43.746644"
  },
  "faq": [
    {
      "question": "Warum ist Hygiene bei der Massage so entscheidend?",
      "answer": "Hygiene schützt sowohl Klienten als auch Therapeuten effektiv vor der Übertragung von Keimen und Bakterien. Saubere Oberflächen schaffen Vertrauen und gewährleisten ein sicheres, angenehmes Ambiente für jede Massage- und Wellnessanwendung."
    },
    {
      "question": "Sind die Reiniger materialverträglich für Massageliegen und Geräte?",
      "answer": "Ja, unsere ausgewählten Desinfektionstücher und Reiniger sind speziell für den professionellen Einsatz konzipiert. Sie reinigen und desinfizieren Oberflächen wie Massageliegen, Therapiestühle und Wellness-Geräte gründlich, ohne das Material zu beschädigen."
    },
    {
      "question": "Wo kann ich diese Desinfektionsmittel überall einsetzen?",
      "answer": "Die Produkte eignen sich ideal für alle Kontaktflächen in Ihrer Massagepraxis oder Ihrem Wellnessbereich: Massageliegen, Armlehnen, Kopfstützen, Griffe von Geräten, Ablagen und weitere Oberflächen, die regelmäßiger Desinfektion bedürfen."
    }
  ],
  "productCount": 0,
  "enhancedAt": "2025-10-11T19:53:43.746669"
}