{
  "categoryId": 66,
  "categoryNameCanonical": "Igelbälle zur Reflexzonenmassage",
  "slug": "igelballe-zur-reflexzonenmassage",
  "parentCategoryId": 65,
  "level": 1,
  "description": "Igelbälle zur Reflexzonenmassage. Finden Sie Entspannung & Wohlbefinden. Bester Preis!",
  "content": "<div><h2>Igelbälle zur Reflexzonenmassage: Ihr Weg zu mehr Wohlbefinden</h2><p>Entdecken Sie die wohltuende Kraft der Igelbälle für eine gezielte Reflexzonenmassage. Diese kleinen, aber wirkungsvollen Helfer sind ideal, um Verspannungen zu lösen, die Durchblutung anzuregen und ein tiefes Gefühl der Entspannung zu fördern. Egal ob nach einem langen Arbeitstag, intensiver körperlicher Betätigung oder einfach für Momente der Ruhe – Igelbälle sind Ihre perfekte Begleitung zu mehr Vitalität und Wohlbefinden.</p><h3>Was sind Igelbälle und wie wirken sie?</h3><p>Igelbälle sind spezielle Massagebälle, die mit zahlreichen kleinen Noppen versehen sind. Diese Noppen üben bei Anwendung einen punktuellen Druck auf die Haut und das darunterliegende Gewebe aus. Bei der Reflexzonenmassage, insbesondere an den Füßen, stimulieren sie gezielt Nervenenden, die mit verschiedenen Organen und Körperbereichen verbunden sind. Dies führt zu einer verbesserten Durchblutung, Lockerung von Faszien und Muskeln sowie einer Aktivierung des gesamten Organismus. Es ist eine einfache, aber hochwirksame Form der Selbst-Massage.</p><h3>Vorteile der Reflexzonenmassage mit Igelbällen</h3><ul><li><strong>Lockerung von Verspannungen:</strong> Gezielter Druck auf Muskeln und Faszien löst effektiv Verhärtungen.</li><li><strong>Förderung der Durchblutung:</strong> Die Stimulation regt die Blutzirkulation an, was zur besseren Versorgung des Gewebes beiträgt.</li><li><strong>Stressabbau:</strong> Die Massage wirkt beruhigend auf das Nervensystem und hilft, Stress abzubauen.</li><li><strong>Schmerzlinderung:</strong> Kann bei Fußschmerzen, Rückenbeschwerden oder Kopfschmerzen unterstützend wirken.</li><li><strong>Verbessertes Wohlbefinden:</strong> Ein ganzheitliches Gefühl von Entspannung und Revitalisierung.</li></ul><h3>Anwendung der Igelbälle für gezielte Entspannung</h3><p>Die Anwendung ist denkbar einfach. Legen Sie den Igelball auf den Boden und rollen Sie Ihre Fußsohle sanft darüber. Variieren Sie den Druck und die Bewegungsrichtung, um alle Bereiche der Fußreflexzonen zu erreichen. Igelbälle können auch für andere Körperpartien wie Rücken, Nacken, Schultern oder Hände verwendet werden. Führen Sie leichte Roll- oder Kreisbewegungen aus, um die gewünschte Massageintensität zu erzielen. Beginnen Sie stets mit leichtem Druck und steigern Sie diesen nach und nach, je nach Ihrem persönlichen Empfinden.</p><h3>Igelbälle kaufen: Top Angebote & Bester Preis</h3><p>Sie suchen hochwertige Igelbälle für Ihre tägliche Massage? In unserem Online-Shop finden Sie eine vielfältige Auswahl an Igelbällen in verschiedenen Größen und Härtegraden. Wir legen Wert auf Qualität und bieten Ihnen Igelbälle, die langlebig und effektiv sind. Profitieren Sie von unserem attraktiven Angebot und sichern Sie sich Igelbälle zum besten Preis. Ein regelmäßiges Angebot ermöglicht es Ihnen, Ihr persönliches Set für eine umfassende Selbst-Massage zusammenzustellen. Steigern Sie Ihr Wohlbefinden mit unseren erstklassigen Igelbällen!</p><h3>Für wen sind Igelbälle geeignet?</h3><p>Igelbälle sind für nahezu jeden geeignet, der Verspannungen lösen, die Durchblutung fördern oder einfach nur entspannen möchte. Ob Sportler zur Regeneration, Büroarbeiter mit Nackenverspannungen oder Menschen, die ihre Fußgesundheit verbessern möchten – die Igelball-Massage ist eine einfache und effektive Methode zur Selbsthilfe. Gönnen Sie sich und Ihrem Körper die wohltuende Wirkung dieser kleinen Helfer und erleben Sie ein neues Maß an Wohlbefinden und Vitalität.</p></div>\n\n```html\n<h3>Top 5 Igelbälle zur Reflexzonenmassage</h3>\n<ul>\n    <li>\n        <strong>Igelball Massageball Advanced Hart - Tiefenmuskulatur & Triggerpunkte</strong> - Gezielte Tiefenmassage für Sportler und bei hartnäckigen Verspannungen. Seine Härte ermöglicht eine effektive Tiefenwirkung, ideal für die intensive Bearbeitung von Triggerpunkten und zur Muskelregeneration nach dem Sport. - Preis: 15.0€\n    </li>\n    <li>\n        <strong>URAQT Massagebälle Premium Set – Ihr Schlüssel zur Tiefenentspannung & Regeneration</strong> - Vielseitiges Set für ganzheitliche Entspannung und sanfte Muskelstimulation. Bietet eine hervorragende Kombination aus Preis und Leistung für allgemeine Wellness und Entspannung im Alltag. Das Set ist ideal für Einsteiger in die Selbstmassage. - Preis: 6.0€\n    </li>\n    <li>\n        <strong>Schildkröt Massagebälle Pro (2er-Set)</strong> - Professionelles Doppelpack für tiefe Muskelregeneration und gezielte Anwendung. Diese Bälle eignen sich hervorragend für die gezielte Selbstmassage und zur Förderung der Durchblutung, besonders im Doppelpack für symmetrische Anwendungen an Rücken oder Füßen. - Preis: 6.0€\n    </li>\n    <li>\n        <strong>Igelball Massageball Advanced Hart - Tiefenmuskulatur & Triggerpunkte</strong> - Unverzichtbar für fortgeschrittene Anwender und gezielte Schmerztherapie. Aufgrund seiner spezifischen Härte ist dieser Ball besonders empfehlenswert für alle, die tiefe muskuläre Beschwerden oder hartnäckige Triggerpunkte effektiv behandeln möchten. Seine Effektivität ist unübertroffen für anspruchsvolle Anwendungen. - Preis: 15.0€\n    </li>\n    <li>\n        <strong>URAQT Massagebälle Premium Set – Ihr Schlüssel zur Tiefenentspannung & Regeneration</strong> - Das ideale Starter-Set für maximale Flexibilität und umfassendes Wohlbefinden. Dieses Premium-Set ist nicht nur preisgünstig, sondern auch vielseitig einsetzbar. Es bietet eine ausgezeichnete Grundlage für regelmäßige Selbstmassagen und zur Förderung der allgemeinen Körperentspannung. - Preis: 6.0€\n    </li>\n</ul>\n```\n\n{'title': 'Vergleich der 1 besten Igelbälle zur Reflexzonenmassage', 'columns': ['Modell', 'Typ', 'Set-Inhalt', 'Material', 'Anwendungsbereiche', 'Zweck', 'Preis', 'Bewertung'], 'products': [{'rank': 1, 'name': 'Schildkröt Massagebälle Pro (2er-Set)', 'typ': 'Massagebälle für Triggerpunkte und Reflexzonen', 'set-inhalt': '2 Bälle', 'material': 'Hochwertiges, hautfreundliches Material', 'anwendungsbereiche': 'Füße, Hände, Nacken, Schultern, Rücken', 'zweck': 'Muskelentspannung, Selbstmassage, Regeneration, Spannungslinderung, Durchblutungsförderung', 'price': '6.0', 'rating': '4.4/5', 'productUrl': '/product/pro-schildkrot-massageballe-2er-set', 'image': 'https://m.media-amazon.com/images/I/71fDdSvxhjL._AC_SL1500_.jpg'}]}",
  "seo": {
    "title": "Igelbälle Reflexzonenmassage: Tiefenentspannung & Wohlbefinden",
    "description": "Igelbälle zur Reflexzonenmassage. Finden Sie Entspannung & Wohlbefinden. Bester Preis!",
    "keywords": [
      "Igelbälle",
      "Reflexzonenmassage",
      "Massagebälle",
      "Fußmassage",
      "Wohlbefinden",
      "Muskelentspannung",
      "Faszienball",
      "Tiefenentspannung",
      "bester Preis",
      "Sonderangebot"
    ],
    "enhancedAt": "2025-10-11T19:52:42.415994"
  },
  "faq": [
    {
      "question": "Was sind Igelbälle und wie funktionieren sie bei der Reflexzonenmassage?",
      "answer": "Igelbälle sind kleine, mit Noppen versehene Bälle, die durch sanften Druck auf spezifische Körperbereiche, insbesondere die Fußsohlen, die Durchblutung fördern und Nervenenden stimulieren. Dies löst Entspannung aus und kann Schmerzen lindern. Sie bieten eine effektive Selbst-Massage."
    },
    {
      "question": "Für welche Körperbereiche kann ich Igelbälle einsetzen?",
      "answer": "Igelbälle eignen sich hervorragend für die Fußreflexzonenmassage, können aber auch gezielt an Rücken, Nacken, Schultern, Händen und Waden zur Muskelentspannung und Faszienlockerung eingesetzt werden. Sie sind vielseitige Begleiter für Ihre persönliche Massage."
    },
    {
      "question": "Welche Vorteile bieten Igelbälle für mein Wohlbefinden?",
      "answer": "Die Anwendung von Igelbällen kann die Durchblutung anregen, Muskelverspannungen lösen, die Beweglichkeit verbessern, Stress reduzieren und zu einem allgemeinen Gefühl der Entspannung und des Wohlbefindens beitragen. Es ist eine einfache und effektive Form der Selbst-Massage für Körper und Geist."
    },
    {
      "question": "Gibt es spezielle Angebote für Igelbälle?",
      "answer": "Ja, in unserem Sortiment finden Sie regelmäßig attraktive Angebote für Igelbälle in verschiedenen Größen und Härtegraden. Achten Sie auf unsere Sonderaktionen, um Igelbälle zum besten Preis zu erwerben und Ihr Wohlbefinden zu steigern. Wir bieten stets faire Preise für hochwertige Produkte."
    },
    {
      "question": "Wie finde ich die richtigen Igelbälle für meine Bedürfnisse?",
      "answer": "Die Wahl der Igelbälle hängt von der gewünschten Intensität ab. Kleinere Bälle mit feineren Noppen sind gut für empfindliche Bereiche, während größere Bälle mit festeren Noppen eine intensivere Massage bieten. Wir beraten Sie gerne bei der Auswahl des passenden Produkts für Ihre individuelle Massage und Ihr Wohlbefinden."
    }
  ],
  "productCount": 0,
  "enhancedAt": "2025-10-11T19:52:42.416011"
}