{
  "categoryId": 71,
  "categoryNameCanonical": "Silikon-Schröpf-Cups",
  "slug": "silikon-schropf-cups",
  "parentCategoryId": 69,
  "level": 1,
  "description": "Entdecken Sie unsere Silikon-Schröpf-Cups für Tiefenmassage und Wellness. Jetzt zum Top-Angebot kaufen!",
  "content": "<div><h2>Silikon-Schröpf-Cups: Ihr Weg zu tiefer Entspannung und besserer Haut</h2><p>Entdecken Sie die wohltuende Kraft der Massage mit unseren hochwertigen Silikon-Schröpf-Cups. Diese innovativen Werkzeuge sind perfekt für alle, die zu Hause eine professionelle Wellness-Erfahrung suchen. Ob zur Linderung von Muskelverspannungen, zur Verbesserung des Hautbildes oder einfach zur tiefen Entspannung – unsere Schröpf-Cups sind eine Bereicherung für Ihr Wohlbefinden.</p><h3>Die Vorteile der Schröpf-Massage mit Silikon-Cups</h3><p>Die Anwendung von Silikon-Schröpf-Cups basiert auf einer jahrhundertealten Technik, die neu interpretiert wurde. Durch das erzeugte Vakuum wird die Durchblutung der Haut und des darunterliegenden Gewebes intensiv angeregt. Dies führt zu einer besseren Versorgung mit Nährstoffen, einem beschleunigten Abtransport von Stoffwechselprodukten und einer spürbaren Entspannung der Muskulatur. Besonders im Bereich der Bindegewebsmassage und bei der Behandlung von Cellulite zeigen unsere Silikon-Schröpf-Cups beeindruckende Ergebnisse. Genießen Sie eine effektive Massage, die Ihre Haut strafft und revitalisiert.</p><h3>Einfache Anwendung für jedermann</h3><p>Unsere Silikon-Schröpf-Cups sind benutzerfreundlich und vielseitig einsetzbar. Tragen Sie einfach etwas Massageöl auf die Haut auf, drücken Sie den Cup zusammen, um die Luft zu entweichen, und setzen Sie ihn auf die Haut. Lassen Sie den Cup los, um ein Vakuum zu erzeugen. Sie können den Cup dann sanft über die Haut gleiten lassen oder ihn für eine statische Anwendung an einer Stelle belassen. Die Flexibilität des Silikons ermöglicht eine präzise Kontrolle der Saugstärke, sodass Sie die Massage genau auf Ihre Bedürfnisse abstimmen können. Perfekt für Gesicht, Nacken, Rücken, Beine und andere Körperbereiche.</p><h3>Qualität und Komfort zum besten Preis</h3><p>Unsere Silikon-Schröpf-Cups sind aus medizinischem, hautfreundlichem Silikon gefertigt, das besonders langlebig und leicht zu reinigen ist. Dieses Material ist nicht nur robust, sondern auch hygienisch und sicher für alle Hauttypen. Wir bieten Ihnen diese effektiven Wellness-Helfer zum besten Preis an. Profitieren Sie von unserem aktuellen Angebot und starten Sie noch heute Ihre persönliche Reise zu mehr Wohlbefinden und einer sichtbar schöneren Haut. Sichern Sie sich jetzt Ihr Set und erleben Sie die umfassenden Vorteile einer professionellen Massage zu Hause!</p></div>\n\n<h3>Top 5 Silikon-Schröpf-Cups</h3>\n<ul>\n    <li><strong>ROSENICE 12-teiliges Silikon Schröpfset (Blau) – Professionelle Tiefenmassage für Körper & Gesicht</strong> - Professionelle Tiefenmassage für Körper & Gesicht, ideal für vielseitige Anwendungen - Preis: 19.0€</li>\n    <li><strong>MYAYD Silikon Schröpfset (4 Stück, L-XS, Weiß)</strong> - Vielseitiges Set für Ganzkörpermassage & Stressabbau mit verschiedenen Größen - Preis: 13.0€</li>\n    <li><strong>DazSpirit Schröpfset Silikon Vakuum Cups (4 Stück) - Blau</strong> - Zur Entspannung & Regeneration mit einfacher Anwendung - Preis: 9.0€</li>\n    <li><strong>Funxim Silikon Schröpfgläser Set (2 Stück) – Ihr digitaler Wellness-Assistent</strong> - Hochwertiges Set für gezielte Anwendungen und ein Gefühl des Wohlbefindens - Preis: 9.0€</li>\n    <li><strong>4er Set Silikon Schröpfgläser für Gesichtsmassage (Rosa)</strong> - Speziell für die Gesichts-Vakuummassage, fördert Durchblutung, Kollagen & Hautelastizität - Preis: 4.0€</li>\n</ul>\n\n{'title': 'Vergleich der 5 besten Silikon-Schröpf-Cups', 'columns': ['Modell', 'Teile im Set', 'Anwendungsbereich', 'Materialqualität', 'Hauptvorteile', 'Farbe', 'Preis', 'Bewertung'], 'products': [{'rank': 1, 'name': 'MYAYD Silikon Schröpfset (4 Stück, L-XS, Weiß)', 'Teile im Set': '4 (verschiedene Größen L-XS)', 'Anwendungsbereich': 'Ganzkörper (Nacken, Schultern, Rücken, Beine)', 'Materialqualität': 'Medizinisches, BPA-freies Silikon', 'Hauptvorteile': 'Stressreduktion, verbesserte Durchblutung, Muskelentspannung, Hautgesundheit, einfache Druckregulierung', 'Farbe': 'Weiß', 'price': '13.0', 'rating': '4.6/5', 'productUrl': '/product/myayd-silikon-schropfset-stuck-l-xs-weiss', 'image': 'https://m.media-amazon.com/images/I/51Fka+NJBPL._AC_SL1002_.jpg'}, {'rank': 2, 'name': 'ROSENICE 12-teiliges Silikon Schröpfset (Blau) – Professionelle Tiefenmassage für Körper & Gesicht', 'Teile im Set': '12', 'Anwendungsbereich': 'Körper & Gesicht (gezielte Bereiche)', 'Materialqualität': 'Robuste, hautverträgliche Silikonbecher', 'Hauptvorteile': 'Professionelle Tiefenmassage, löst Verspannungen, fördert Durchblutung, verbessert Hautbild', 'Farbe': 'Blau', 'price': '19.0', 'rating': '4.3/5', 'productUrl': '/product/12-teiliges-rosenice-silikon-schropfset-blau-professionelle', 'image': 'https://m.media-amazon.com/images/I/61u209vq4VL._AC_SL1280_.jpg'}, {'rank': 3, 'name': 'DazSpirit Schröpfset Silikon Vakuum Cups (4 Stück) - Blau', 'Teile im Set': '4', 'Anwendungsbereich': 'Ganzkörper (passt sich jeder Körperkontur an)', 'Materialqualität': 'Flexible Silikonkonstruktion', 'Hauptvorteile': 'Entspannung, Regeneration, Linderung von Muskelverspannungen, fördert Durchblutung', 'Farbe': 'Blau', 'price': '9.0', 'rating': '4.3/5', 'productUrl': '/product/dazspirit-schropfset-silikon-vakuum-cups-stuck', 'image': 'https://m.media-amazon.com/images/I/71IbSheGenL._SL1500_.jpg'}, {'rank': 4, 'name': 'Funxim Silikon Schröpfgläser Set (2 Stück) – Ihr digitaler Wellness-Assistent', 'Teile im Set': '2', 'Anwendungsbereich': 'Vielseitig (Körper & Gesicht für Wellness)', 'Materialqualität': 'Silikon (Standardqualität)', 'Hauptvorteile': 'Basisanwendung für Wohlbefinden, einfache Handhabung', 'Farbe': 'Transparent', 'price': '9.0', 'rating': '4.4/5', 'productUrl': '/product/funxim-silikon-schropfglaser-set-stuck-ihr', 'image': 'https://m.media-amazon.com/images/I/618afT-lpgL._AC_SL1500_.jpg'}, {'rank': 5, 'name': '4er Set Silikon Schröpfgläser für Gesichtsmassage (Rosa)', 'Teile im Set': '4', 'Anwendungsbereich': 'Gesicht (Stirn, Wangen, Augenpartie)', 'Materialqualität': 'Hochwertiges, medizinisches Silikon', 'Hauptvorteile': 'Gesichtsverjüngung, Hautstraffung, fördert Durchblutung/Kollagenproduktion, Anti-Aging, Reduzierung feiner Linien', 'Farbe': 'Rosa', 'price': '4.0', 'rating': '3.7/5', 'productUrl': '/product/4er-set-silikon-schropfglaser-fur-gesichtsmassage', 'image': 'https://m.media-amazon.com/images/I/61VXi5Y9L2L._AC_UL320_.jpg'}]}",
  "seo": {
    "title": "Silikon-Schröpf-Cups für Massage & Wellness – Bester Preis!",
    "description": "Entdecken Sie unsere Silikon-Schröpf-Cups für Tiefenmassage und Wellness. Jetzt zum Top-Angebot kaufen!",
    "keywords": [
      "Silikon-Schröpf-Cups",
      "Massage Schröpfen",
      "Wellness Cups",
      "bester Preis Schröpfen",
      "Schröpf-Angebot",
      "Bindegewebsmassage",
      "Cellulite-Behandlung",
      "Hautstraffung",
      "Vakuum-Massage"
    ],
    "enhancedAt": "2025-10-11T19:53:15.230065"
  },
  "faq": [
    {
      "question": "Wie funktionieren Silikon-Schröpf-Cups für die Massage?",
      "answer": "Silikon-Schröpf-Cups erzeugen durch Zusammendrücken und Aufsetzen auf die Haut ein Vakuum. Dieser Unterdruck hebt die Haut sanft an, fördert die Durchblutung und löst Verspannungen im Gewebe. Die Cups können gleitend oder statisch angewendet werden, um verschiedene Massageeffekte zu erzielen."
    },
    {
      "question": "Welche Vorteile bieten Silikon-Schröpf-Cups für mein Wohlbefinden?",
      "answer": "Die regelmäßige Anwendung von Silikon-Schröpf-Cups kann die Durchblutung verbessern, Muskelverspannungen lindern, die Lymphdrainage anregen und das Hautbild straffen. Sie sind ideal für eine entspannende Selbstmassage und tragen zur allgemeinen Wellness bei. Viele nutzen sie auch zur Reduzierung von Cellulite."
    },
    {
      "question": "Wie reinige ich meine Silikon-Schröpf-Cups nach der Anwendung?",
      "answer": "Die Reinigung ist denkbar einfach. Spülen Sie die Silikon-Schröpf-Cups nach jeder Anwendung unter warmem Wasser mit etwas Seife ab. Lassen Sie sie anschließend an der Luft trocknen. Das hochwertige Silikonmaterial ist hygienisch und langlebig, was eine einfache Pflege gewährleistet."
    }
  ],
  "productCount": 0,
  "enhancedAt": "2025-10-11T19:53:15.230077"
}