{
  "productId": "3742329227",
  "name": "Das Airfryer-Kochbuch: Vegan: 70 schnelle, einfache und gesunde Rezepte | Maximal 30 Minuten | Pflanzliche Gerichte: Sandwiches, Bowls, Gebäck (Kochen mit dem Airfryer)",
  "slug": "das-airfryer-kochbuch-vegan-70-schnelle-einfache-u",
  "description": "",
  "shortDescription": "Das Airfryer-Kochbuch: Vegan: 70 schnelle, einfache und gesunde Rezepte | Maximal 30 Minuten | Pflan",
  "price": "20.0",
  "compareAtPrice": 23,
  "images": [
    "https://m.media-amazon.com/images/I/71ScB3fTWJL._SL1500_.jpg",
    "https://m.media-amazon.com/images/I/71fjgM2F28L._SL1500_.jpg",
    "https://m.media-amazon.com/images/I/71qWHJJi1BL._SL1500_.jpg",
    "https://m.media-amazon.com/images/I/71C0YcjaR4L._SL1500_.jpg",
    "https://m.media-amazon.com/images/I/61U7LTezR6L._SL1500_.jpg"
  ],
  "videos": [
    "https://m.media-amazon.com/images/S/vse-vms-transcoding-artifact-eu-west-1-prod/e5aed101-1897-4bbf-915b-dd52aa6a351a/default.jobtemplate.hls.m3u8"
  ],
  "category": "airfryer anleitung",
  "tags": [
    "producto",
    "das",
    "airfryer anleitung"
  ],
  "amazonUrl": "https://amazon.de/dp/3742329227?tag=clickclickh0b-21",
  "amazonASIN": "3742329227",
  "affiliateId": "clickclickh0b-21",
  "originalAmazonTitle": "Das Airfryer-Kochbuch: Vegan: 70 schnelle, einfache und gesunde Rezepte | Maximal 30 Minuten | Pflanzliche Gerichte: Sandwiches, Bowls, Gebäck (Kochen mit dem Airfryer)",
  "amazonPrice": "20.0€",
  "amazonRating": 5.0,
  "amazonReviewCount": 0,
  "brand": "Das",
  "seo": {
    "title": "Das Airfryer-Kochbuch: Vegan: 70 schnelle, einfache und gesunde Rezepte | Maximal 30 Minuten | Pflanzliche Gerichte: Sandwiches, Bowls, Gebäck (Kochen mit dem Airfryer) - Product Expert",
    "description": "Découvrez Das Airfryer-Kochbuch: Vegan: 70 schnelle, einfache und gesunde Rezepte | Maximal 30 Minuten | Pflanzliche Gerichte: Sandwiches, Bowls, Gebäck (Kochen mit dem Airfryer) sur Amazon. Note 5.0/5 avec 0 avis.",
    "keywords": [
      "producto",
      "das",
      "amazon",
      "avis"
    ]
  },
  "reviews": {
    "averageRating": 5.0,
    "totalReviews": 0,
    "breakdown": {
      "5": 60,
      "4": 25,
      "3": 10,
      "2": 3,
      "1": 2
    }
  }
}