{
  "productId": "B007TIY3RW",
  "name": "3B Scientific Lehrtafel laminiert - Das Nervensystem",
  "slug": "scientific-lehrtafel-laminiert-das-nervensystem",
  "description": "<div><h2>3B Scientific Lehrtafel laminiert - Das Nervensystem</h2><p>Quality product</p></div>",
  "shortDescription": "3B Scientific Lehrtafel laminiert - Das Nervensystem - Quality Product",
  "price": "27.0",
  "compareAtPrice": 31,
  "images": [
    "https://m.media-amazon.com/images/I/A1pZv+FTbTL._AC_UL320_.jpg"
  ],
  "videos": [],
  "category": "Anatomie-Poster für Therapeuten",
  "tags": [
    "3b",
    "anatomie-poster für therapeuten"
  ],
  "amazonUrl": "https://amazon.de/dp/B007TIY3RW/?tag=clickclickh0b-21",
  "amazonASIN": "B007TIY3RW",
  "affiliateId": "clickclickh0b-21",
  "originalAmazonTitle": "3B Scientific Lehrtafel laminiert - Das Nervensystem",
  "amazonPrice": "27.0€",
  "amazonRating": 4.4,
  "amazonReviewCount": 0,
  "brand": "3B",
  "seo": {
    "title": "3B Scientific Lehrtafel laminiert - Das Nervensystem",
    "description": "3B Scientific Lehrtafel laminiert - Das Nervensystem - Quality Product",
    "keywords": [
      "3b scientific lehrtafel laminiert - das nervensystem",
      "anatomie-poster für therapeuten",
      "3b"
    ],
    "ogTitle": "3B Scientific Lehrtafel laminiert - Das Nervensystem",
    "ogDescription": "3B Scientific Lehrtafel laminiert - Das Nervensystem - Quality Product"
  },
  "reviews": {
    "averageRating": 4.4,
    "totalReviews": 0,
    "breakdown": {
      "5": 60,
      "4": 25,
      "3": 10,
      "2": 3,
      "1": 2
    }
  },
  "specifications": {
    "Quality": "High",
    "Warranty": "2 years"
  },
  "faq": [
    {
      "q": "Is it good quality?",
      "a": "Yes, high quality product."
    }
  ],
  "enhancedAt": "2025-10-10T22:49:24.010493",
  "originalName": "3B Scientific Lehrtafel laminiert - Das Nervensystem",
  "enhanced": true
}