{
  "productId": "B071FC23QW",
  "name": "Electrolux AEG 2193712110 ORIGINAL Handgriff Griffstück Griff Staubsaugerschlauch Saugschlauch Staubsauger",
  "slug": "electrolux-aeg-2193712110-original-handgriff-griff",
  "description": "",
  "shortDescription": "Electrolux AEG 2193712110 ORIGINAL Handgriff Griffstück Griff Staubsaugerschlauch Saugschlauch Staub",
  "price": "25.58",
  "compareAtPrice": 29,
  "images": [
    "https://m.media-amazon.com/images/I/41m3OIXpsvL._AC_SL1200_.jpg",
    "https://m.media-amazon.com/images/I/31m4hDgno8L._AC_.jpg"
  ],
  "videos": [],
  "category": "staubsauger griff",
  "tags": [
    "producto",
    "besuche den aeg-store",
    "staubsauger griff"
  ],
  "amazonUrl": "https://amazon.de/dp/B071FC23QW?tag=clickclickh0b-21",
  "amazonASIN": "B071FC23QW",
  "affiliateId": "clickclickh0b-21",
  "originalAmazonTitle": "Electrolux AEG 2193712110 ORIGINAL Handgriff Griffstück Griff Staubsaugerschlauch Saugschlauch Staubsauger",
  "amazonPrice": "25.58€",
  "amazonRating": 4.4,
  "amazonReviewCount": 0,
  "brand": "Besuche den AEG-Store",
  "seo": {
    "title": "Electrolux AEG 2193712110 ORIGINAL Handgriff Griffstück Griff Staubsaugerschlauch Saugschlauch Staubsauger - Product Expert",
    "description": "Découvrez Electrolux AEG 2193712110 ORIGINAL Handgriff Griffstück Griff Staubsaugerschlauch Saugschlauch Staubsauger sur Amazon. Note 4.4/5 avec 0 avis.",
    "keywords": [
      "producto",
      "besuche den aeg-store",
      "amazon",
      "avis"
    ]
  },
  "reviews": {
    "averageRating": 4.4,
    "totalReviews": 0,
    "breakdown": {
      "5": 60,
      "4": 25,
      "3": 10,
      "2": 3,
      "1": 2
    }
  }
}