{
  "productId": "B07GFJ6FZV",
  "name": "vhbw 5X Staubsaugerbeutel kompatibel mit elta VC 301 Staubsauger - Mikrovlies, 31,5cm x 30cm Weiß",
  "slug": "vhbw-5x-staubsaugerbeutel-kompatibel-mit-elta-vc-3",
  "description": "Staubsaugertüten passend für Staubsauger | Erhalten die Saugkraft und verhindern zuverlässig Geruchsbildung | Ersatz für Y101, 7060001, Typ G | Hochwertige, kompatible Staubbeutel aus Mikrovlies | Material: Mikrovlies | Länge: 31,5 cm | Breite: 30 cm | Farbe: weiß | Lieferumfang: 5x Staubsaugerbeutel | Zubehör und Ersatzteile für Staubsauger - von vhbw",
  "shortDescription": "vhbw 5X Staubsaugerbeutel kompatibel mit elta VC 301 Staubsauger - Mikrovlies, 31,5cm x 30cm Weiß",
  "price": "10.69",
  "compareAtPrice": 12,
  "images": [
    "https://m.media-amazon.com/images/I/716iZ9bVU5L._AC_SL1500_.jpg",
    "https://m.media-amazon.com/images/I/81fkxX1EDuL._AC_SL1500_.jpg",
    "https://m.media-amazon.com/images/I/31j6mJzCUgL._AC_.jpg",
    "https://m.media-amazon.com/images/I/414NDQSEepL._AC_.jpg"
  ],
  "videos": [],
  "category": "staubsauger elta",
  "tags": [
    "producto",
    "besuche den vhbw-store",
    "staubsauger elta"
  ],
  "amazonUrl": "https://amazon.de/dp/B07GFJ6FZV?tag=clickclickh0b-21",
  "amazonASIN": "B07GFJ6FZV",
  "affiliateId": "clickclickh0b-21",
  "originalAmazonTitle": "vhbw 5X Staubsaugerbeutel kompatibel mit elta VC 301 Staubsauger - Mikrovlies, 31,5cm x 30cm Weiß",
  "amazonPrice": "10.69€",
  "amazonRating": 0,
  "amazonReviewCount": 0,
  "brand": "Besuche den vhbw-Store",
  "seo": {
    "title": "vhbw 5X Staubsaugerbeutel kompatibel mit elta VC 301 Staubsauger - Mikrovlies, 31,5cm x 30cm Weiß - Product Expert",
    "description": "Découvrez vhbw 5X Staubsaugerbeutel kompatibel mit elta VC 301 Staubsauger - Mikrovlies, 31,5cm x 30cm Weiß sur Amazon. Note 0/5 avec 0 avis.",
    "keywords": [
      "producto",
      "besuche den vhbw-store",
      "amazon",
      "avis"
    ]
  },
  "reviews": {
    "averageRating": 0,
    "totalReviews": 0,
    "breakdown": {
      "5": 60,
      "4": 25,
      "3": 10,
      "2": 3,
      "1": 2
    }
  }
}