{
  "productId": "B089YXRD1R",
  "name": "Makita VC2000L Staubsauger f. Staubklasse L, Keine Farbe.",
  "slug": "makita-vc2000l-staubsauger-f-staubklasse-l-keine-f",
  "description": "Für Stäube mit MAK Werten > 1 mg/m³ und Staubklasse L nach Euronorm | Für Nass- und Trockenbetrieb | Mit Push und Clean Filterreinigungssystem | Praktische Kabelhalterung",
  "shortDescription": "Makita VC2000L Staubsauger f. Staubklasse L, Keine Farbe.",
  "price": "137.99",
  "compareAtPrice": 158,
  "images": [
    "https://m.media-amazon.com/images/I/711ZabrD3hL._AC_SL1500_.jpg",
    "https://m.media-amazon.com/images/I/71qfEI4yOwL._AC_SL1500_.jpg",
    "https://m.media-amazon.com/images/I/71GnnRNjbML._AC_SL1500_.jpg",
    "https://m.media-amazon.com/images/I/71A9RgfE4LL._AC_SL1500_.jpg",
    "https://m.media-amazon.com/images/I/71xTAsax0EL._AC_SL1500_.jpg"
  ],
  "videos": [],
  "category": "staubsauger makita",
  "tags": [
    "producto",
    "besuche den makita-store",
    "staubsauger makita"
  ],
  "amazonUrl": "https://amazon.de/dp/B089YXRD1R?tag=clickclickh0b-21",
  "amazonASIN": "B089YXRD1R",
  "affiliateId": "clickclickh0b-21",
  "originalAmazonTitle": "Makita VC2000L Staubsauger f. Staubklasse L, Keine Farbe.",
  "amazonPrice": "137.99€",
  "amazonRating": 4.4,
  "amazonReviewCount": 0,
  "brand": "Besuche den Makita-Store",
  "seo": {
    "title": "Makita VC2000L Staubsauger f. Staubklasse L, Keine Farbe. - Product Expert",
    "description": "Découvrez Makita VC2000L Staubsauger f. Staubklasse L, Keine Farbe. sur Amazon. Note 4.4/5 avec 0 avis.",
    "keywords": [
      "producto",
      "besuche den makita-store",
      "amazon",
      "avis"
    ]
  },
  "reviews": {
    "averageRating": 4.4,
    "totalReviews": 0,
    "breakdown": {
      "5": 60,
      "4": 25,
      "3": 10,
      "2": 3,
      "1": 2
    }
  }
}