{
  "productId": "B08P253ZL8",
  "name": "Comprar smartGyro Speedway Pro. Patinete 1000W 60Km DGT.",
  "slug": "comprar-smartgyro-speedway-pro-patinete-1000w-60km",
  "description": "<div>\n    <h2>Comprar smartGyro Speedway Pro: Patinete Eléctrico 1000W, 60Km, DGT</h2>\n    <p>¿Buscas el patinete eléctrico definitivo en España? Descubre el potente <b>smartGyro Speedway Pro</b>, diseñado para ofrecerte la máxima potencia, autonomía y seguridad. Este patinete te garantiza un rendimiento superior y una experiencia de conducción inigualable en cada trayecto urbano o interurbano.</p>\n    <h3>Características Destacadas</h3>\n    <ul>\n        <li><b>Potencia Extrema 1000W</b>: Su motor de <b>1000W</b> te proporciona una aceleración formidable y la capacidad para afrontar cualquier pendiente sin esfuerzo.</li>\n        <li><b>Autonomía Impresionante 60Km</b>: Disfruta de hasta <b>60Km</b> de recorrido con una sola carga, perfecto para tus desplazamientos diarios y aventuras.</li>\n        <li><b>Homologado DGT para España</b>: Circula con total tranquilidad y legalidad, ya que el smartGyro Speedway Pro cumple con la normativa vigente de la DGT.</li>\n    </ul>\n    <p>No esperes más para experimentar la movilidad del futuro. Consigue tu <b>smartGyro Speedway Pro</b> hoy mismo por solo <b>633.99€</b>. ¡Aprovecha nuestro <b>envío gratis</b> a toda España y recíbelo cómodamente en tu casa! ¡Compra ya y revoluciona tu forma de moverte!</p>\n</div>",
  "shortDescription": "Comprar smartGyro Speedway Pro: Patinete Eléctrico 1000W, 60Km, DGT. ¡Homologado y potente!",
  "price": "633.99",
  "compareAtPrice": 729,
  "images": [
    "https://m.media-amazon.com/images/I/611-A+D-m7L._AC_SL1500_.jpg",
    "https://m.media-amazon.com/images/I/5159Em7lZ9L._AC_SL1500_.jpg",
    "https://m.media-amazon.com/images/I/71zLjYHDfHL._AC_SL1500_.jpg"
  ],
  "videos": [],
  "category": "patinete electrico adultos homologado dgt",
  "tags": [
    "producto",
    "visita la tienda de smartgyro",
    "patinete electrico adultos homologado dgt"
  ],
  "amazonUrl": "https://amazon.es/dp/B08P253ZL8?tag=clickclickh02-21",
  "amazonASIN": "B08P253ZL8",
  "affiliateId": "clickclickh02-21",
  "originalAmazonTitle": "smartGyro Speedway Pro - Patinete Eléctrico de 48V, 1000W Pot. Máxima, Batería 15Ah, Autonomía 60 Km, Ruedas de 10 Pulgadas Dual Grip, Suspensiones, Triple Frenada, Certificado DGT",
  "amazonPrice": "633.99€",
  "amazonRating": 4.0,
  "amazonReviewCount": 0,
  "brand": "Visita la tienda de SMARTGYRO",
  "seo": {
    "title": "Comprar smartGyro Speedway Pro. Patinete 1000W 60Km DGT.",
    "description": "Comprar smartGyro Speedway Pro: Patinete Eléctrico 1000W, 60Km, DGT. ¡Homologado y potente!",
    "keywords": "Comprar smartGyro Speedway Pro. Patinete 1000W 60Km DGT., producto, calidad, precio",
    "ogTitle": "Comprar smartGyro Speedway Pro. Patinete 1000W 60Km DGT.",
    "ogDescription": "Comprar smartGyro Speedway Pro: Patinete Eléctrico 1000W, 60Km, DGT. ¡Homologado y potente!"
  },
  "reviews": {
    "averageRating": 4.0,
    "totalReviews": 0,
    "breakdown": {
      "5": 60,
      "4": 25,
      "3": 10,
      "2": 3,
      "1": 2
    }
  },
  "specifications": {
    "Garantía": "2 años",
    "Envío": "Gratis a toda España",
    "Disponibilidad": "Inmediata"
  },
  "faq": [
    {
      "question": "¿Por qué elegir Comprar smartGyro Speedway Pro: Patinete Eléctrico 1000W, 60Km, DGT?",
      "answer": "Comprar smartGyro Speedway Pro: Patinete Eléctrico 1000W, 60Km, DGT ofrece la mejor calidad al mejor precio."
    },
    {
      "question": "¿Hay garantía?",
      "answer": "Sí, todos nuestros productos incluyen garantía completa."
    }
  ],
  "enhancedAt": "2025-10-07T18:42:01.394051",
  "originalName": "Comprar smartGyro Speedway Pro: Patinete Eléctrico 1000W, 60Km, DGT",
  "enhanced": true
}