{
  "productId": "B09H2C6MZL",
  "name": "Sharplace 10 Paires D'hélices en Fibre de Carbone 5030 5x3 CW/CCW pour Quadrotor",
  "slug": "sharplace-10-paires-dhelices-en-fibre-de-carbone-5",
  "description": ". Matériau du produit: Plastique | . Couleur orange | . 10 paires de 5030 hélices Pour 250mm Quadcopter Prop, etc | . Durée: env. 5 pouces | . Pitch: env. 3inches",
  "shortDescription": "Sharplace 10 Paires D'hélices en Fibre de Carbone 5030 5x3 CW/CCW pour Quadrotor",
  "price": "11.0",
  "compareAtPrice": 12,
  "images": [
    "https://m.media-amazon.com/images/I/61+AqqqCOUL._AC_UL320_.jpg"
  ],
  "videos": [],
  "category": "Hélices en Fibre de Carbone",
  "tags": [
    "marque : sharplace",
    "hélices en fibre de carbone"
  ],
  "amazonUrl": "https://amazon.fr/dp/B09H2C6MZL/?tag=clickclickh01-21",
  "amazonASIN": "B09H2C6MZL",
  "affiliateId": "clickclickh01-21",
  "originalAmazonTitle": "Sharplace 10 Paires D'hélices en Fibre de Carbone 5030 5x3 CW/CCW pour Quadrotor",
  "amazonPrice": "11.0€",
  "amazonRating": 0,
  "amazonReviewCount": 0,
  "brand": "Marque : Sharplace",
  "seo": {
    "title": "",
    "description": "",
    "keywords": []
  },
  "reviews": {
    "averageRating": 0,
    "totalReviews": 0,
    "breakdown": {
      "5": 60,
      "4": 25,
      "3": 10,
      "2": 3,
      "1": 2
    }
  }
}