{
  "productId": "B0DZX2Q17S",
  "name": "Vuzmode 3 Stück Seitenbürsten-Silikon-O-Ring und 2 Stück Lidar-Silikon-O-Ring, for 65 70 75e 75 80 85 D75 D80 D85 Staubsauger-Ersatzteil Gummiriemen für Staubsauger",
  "slug": "vuzmode-3-stück-seitenbürsten-silikon-o-ring-und-2",
  "description": "",
  "shortDescription": "Vuzmode 3 Stück Seitenbürsten-Silikon-O-Ring und 2 Stück Lidar-Silikon-O-Ring, for 65 70 75e 75 80 8",
  "price": "15.02",
  "compareAtPrice": 17,
  "images": [
    "https://m.media-amazon.com/images/I/51G5i75lkML._AC_UL320_.jpg"
  ],
  "videos": [],
  "category": "staubsauger ring",
  "tags": [
    "producto",
    "marke: vuzmode",
    "staubsauger ring"
  ],
  "amazonUrl": "https://amazon.de/dp/B0DZX2Q17S?tag=clickclickh0b-21",
  "amazonASIN": "B0DZX2Q17S",
  "affiliateId": "clickclickh0b-21",
  "originalAmazonTitle": "Vuzmode 3 Stück Seitenbürsten-Silikon-O-Ring und 2 Stück Lidar-Silikon-O-Ring, for 65 70 75e 75 80 85 D75 D80 D85 Staubsauger-Ersatzteil Gummiriemen für Staubsauger",
  "amazonPrice": "15.02€",
  "amazonRating": 0,
  "amazonReviewCount": 0,
  "brand": "Marke: Vuzmode",
  "seo": {
    "title": "Vuzmode 3 Stück Seitenbürsten-Silikon-O-Ring und 2 Stück Lidar-Silikon-O-Ring, for 65 70 75e 75 80 85 D75 D80 D85 Staubsauger-Ersatzteil Gummiriemen für Staubsauger - Product Expert",
    "description": "Découvrez Vuzmode 3 Stück Seitenbürsten-Silikon-O-Ring und 2 Stück Lidar-Silikon-O-Ring, for 65 70 75e 75 80 85 D75 D80 D85 Staubsauger-Ersatzteil Gummiriemen für Staubsauger sur Amazon. Note 0/5 avec 0 avis.",
    "keywords": [
      "producto",
      "marke: vuzmode",
      "amazon",
      "avis"
    ]
  },
  "reviews": {
    "averageRating": 0,
    "totalReviews": 0,
    "breakdown": {
      "5": 60,
      "4": 25,
      "3": 10,
      "2": 3,
      "1": 2
    }
  }
}