{
  "productId": "B0F1KCYWVZ",
  "name": "2x Bio Lavendelöl Ätherisches Öl - 10ml | Entspannung & Aromatherapie",
  "slug": "10ml-bio-lavendelol-atherisches-entspannung-aromatherapie",
  "description": "<div><h2>2x Bio Lavendelöl Ätherisches Öl - 10ml | Entspannung & Aromatherapie</h2><p>Quality product</p></div>",
  "shortDescription": "2x Bio Lavendelöl Ätherisches Öl - 10ml | Entspannung & Aromatherapie - Quality Product",
  "price": "5.0",
  "compareAtPrice": 5,
  "images": [
    "https://m.media-amazon.com/images/I/71L306FehGL._AC_SL1500_.jpg",
    "https://m.media-amazon.com/images/I/71ujz7SCnGL._AC_SL1500_.jpg",
    "https://m.media-amazon.com/images/I/71N47y0QixL._AC_SL1500_.jpg",
    "https://m.media-amazon.com/images/I/71Ps4d4XYEL._AC_SL1500_.jpg",
    "https://m.media-amazon.com/images/I/71TOZoQJmFL._AC_SL1500_.jpg"
  ],
  "videos": [],
  "category": "Lavendelöl zur Entspannung",
  "tags": [
    "marke: asitanie",
    "lavendelöl zur entspannung"
  ],
  "amazonUrl": "https://amazon.de/dp/B0F1KCYWVZ/?tag=clickclickh0b-21",
  "amazonASIN": "B0F1KCYWVZ",
  "affiliateId": "clickclickh0b-21",
  "originalAmazonTitle": "2 PCS Lavendelöl ätherisches öl Bio Rein Natürlich Lavendel öl Lavender Essential Oil Tropfer-Design Zur Verwendung in Diffusoren Duftöle für Diffusor, Luftbefeuchter, Entspannen, Massage, Bad(10ml)",
  "amazonPrice": "5.0€",
  "amazonRating": 5.0,
  "amazonReviewCount": 0,
  "brand": "Marke: Asitanie",
  "seo": {
    "title": "2x Bio Lavendelöl Ätherisches Öl - 10ml | Entspannung & Aromatherapie",
    "description": "2x Bio Lavendelöl Ätherisches Öl - 10ml | Entspannung & Aromatherapie - Quality Product",
    "keywords": [
      "2x bio lavendelöl ätherisches öl - 10ml | entspannung & aromatherapie",
      "lavendelöl zur entspannung",
      "marke: asitanie"
    ],
    "ogTitle": "2x Bio Lavendelöl Ätherisches Öl - 10ml | Entspannung & Aromatherapie",
    "ogDescription": "2x Bio Lavendelöl Ätherisches Öl - 10ml | Entspannung & Aromatherapie - Quality Product"
  },
  "reviews": {
    "averageRating": 5.0,
    "totalReviews": 0,
    "breakdown": {
      "5": 60,
      "4": 25,
      "3": 10,
      "2": 3,
      "1": 2
    }
  },
  "specifications": {
    "Quality": "High",
    "Warranty": "2 years"
  },
  "faq": [
    {
      "q": "Is it good quality?",
      "a": "Yes, high quality product."
    }
  ],
  "originalName": "2x Bio Lavendelöl Ätherisches Öl - 10ml | Entspannung & Aromatherapie",
  "enhancedAt": "2025-10-10T23:36:24.990870",
  "enhanced": true
}