{
  "productId": "B0FBRD9FKB",
  "name": "bdfndjnm T-Con-Karte V15 Ultra HDTV, kompatibel mit Sony 6870c-0553a/LG-Monitor Tm120 LGE Ver1.0",
  "slug": "bdfndjnm-t-con-karte-v15-ultra-hdtv-kompatibel-mit",
  "description": "GARANTIERTE KOMPATIBILITÄT: T-Con Board V15 Ultra HDTV, kompatibel mit 6870c-0553a/Monitor Tm120 Lge Ver1.0-Fernsehern. Dieses Motherboard gewährleistet nahtlose Integration und konstante Leistung. | ZUVERLÄSSIGER AUSTAUSCH: Ersetzen Sie defekte Treiberplatinen durch unsere hochwertigen Produkte, um häufige TV-Probleme wie keine Anzeige, verzerrte Bilder oder Tonprobleme zu lösen. | OEM-Standardqualität: Hergestellt nach OEM-Standards mit der gleichen Haltbarkeit und Funktionalität wie die Originalplatine. | EINFACHE INSTALLATION: for den direkten Austausch in Eigenregie konzipiert, wodurch Sie Geld for professionelle Reparaturdienste sparen. | Vollständig getestet: Jede Platine wird strengen Tests unterzogen, um eine überragende Leistung und langfristige Zuverlässigkeit sicherzustellen.",
  "shortDescription": "bdfndjnm T-Con-Karte V15 Ultra HDTV, kompatibel mit Sony 6870c-0553a/LG-Monitor Tm120 LGE Ver1.0",
  "price": "28.32",
  "compareAtPrice": 32,
  "images": [
    "https://m.media-amazon.com/images/I/614QqtfnYSL._AC_SL1500_.jpg",
    "https://m.media-amazon.com/images/I/51Qrh5sDIML._AC_SL1500_.jpg",
    "https://m.media-amazon.com/images/I/61MAdEjZuDL._AC_SL1500_.jpg",
    "https://m.media-amazon.com/images/I/51TYzpnoyPL._AC_SL1500_.jpg",
    "https://m.media-amazon.com/images/I/51l5WmejFGL._AC_SL1500_.jpg"
  ],
  "videos": [],
  "category": "staubsauger sony",
  "tags": [
    "producto",
    "marke: bdfndjnm",
    "staubsauger sony"
  ],
  "amazonUrl": "https://amazon.de/dp/B0FBRD9FKB?tag=clickclickh0b-21",
  "amazonASIN": "B0FBRD9FKB",
  "affiliateId": "clickclickh0b-21",
  "originalAmazonTitle": "bdfndjnm T-Con-Karte V15 Ultra HDTV, kompatibel mit Sony 6870c-0553a/LG-Monitor Tm120 LGE Ver1.0",
  "amazonPrice": "28.32€",
  "amazonRating": 0,
  "amazonReviewCount": 0,
  "brand": "Marke: bdfndjnm",
  "seo": {
    "title": "bdfndjnm T-Con-Karte V15 Ultra HDTV, kompatibel mit Sony 6870c-0553a/LG-Monitor Tm120 LGE Ver1.0 - Product Expert",
    "description": "Découvrez bdfndjnm T-Con-Karte V15 Ultra HDTV, kompatibel mit Sony 6870c-0553a/LG-Monitor Tm120 LGE Ver1.0 sur Amazon. Note 0/5 avec 0 avis.",
    "keywords": [
      "producto",
      "marke: bdfndjnm",
      "amazon",
      "avis"
    ]
  },
  "reviews": {
    "averageRating": 0,
    "totalReviews": 0,
    "breakdown": {
      "5": 60,
      "4": 25,
      "3": 10,
      "2": 3,
      "1": 2
    }
  }
}